control.v
module control(input [3:0] opcode,
               output reg regwrite, memwrite,
               output reg alusrc, memtoreg,
               output reg branch,
               output reg [2:0] aluop);

    always @(*) begin
        
        case(opcode)
            4'h1: begin // addi
                regwrite=1; alusrc=1; memtoreg=0; memwrite=0; branch=0; aluop=0;
            end
            4'h2: begin // add
                regwrite=1; alusrc=0; memtoreg=0; memwrite=0; branch=0; aluop=0;
            end
            4'h3: begin // sw
                regwrite=0; alusrc=1; memwrite=1; branch=0; aluop=0;
            end
            4'h4: begin // lw
                regwrite=1; alusrc=1; memtoreg=1; memwrite=0; branch=0; aluop=0;
            end
            4'h5: begin // beq
                regwrite=0; branch=1; aluop=1;
            end
            default: begin // nop
                regwrite=0; memwrite=0; branch=0;
            end
        endcase
    end
endmodule

dmem.v
module dmem(input clk,
            input we,
            input [15:0] addr,
            input [15:0] wd,
            output [15:0] rd);

    reg [15:0] memory [0:15];

    assign rd = memory[addr[3:0]];

        integer i;

        initial begin
        for (i = 0; i < 16; i = i + 1)
                memory[i] = 0;
        end
    always @(posedge clk)
        if (we) memory[addr[3:0]] <= wd;
endmodule

alu.v
module alu(input [15:0] a, b,
           input [2:0] op,
           output reg [15:0] result,
           output zero);

    always @(*) begin
        case(op)
            3'b000: result = a + b;
            3'b001: result = a - b;
            3'b010: result = a & b;
            3'b011: result = a | b;
            default: result = 0;
        endcase
    end

    assign zero = (result == 0);
endmodule

regfile.v
module regfile(input clk,
               input we,
               input [3:0] rs1, rs2, rd,
               input [15:0] wd,
               output [15:0] rd1, rd2, rd_val);

    reg [15:0] regs [0:15];

    assign rd1 = regs[rs1];
    assign rd2 = regs[rs2];
    assign rd_val = regs[rd];

    integer i;
    initial begin
      for(i=0;i<16;i=i+1)
        regs[i]=0;
    end

    always @(posedge clk)
        if (we && rd != 0) regs[rd] <= wd;
endmodule

imem.v
// imem.v
`timescale 1ns/1ps

module imem (
    input  wire [15:0] addr,
    output wire [15:0] instr
);

    reg [15:0] memory [0:255]; // 256 words = 512 bytes instruction memory

    // Initialize with test program
    initial begin
        // R-Type logic: Opcode(3)|Rs(3)|Rt(3)|Rd(3)|Ignored(4)
        // I-Type logic: Opcode(3)|Rs(3)|Rt(3)|Imm(7)

        // Addr 0: LW R1, R0, 0    => Op(010)|Rs(000)|Rt(001)|Imm(0000000) => 010_000_001_0000000 = 16'b0100_0000_1000_0000 = 16'h4080
        // Addr 1: LW R2, R0, 1    => Op(010)|Rs(000)|Rt(010)|Imm(0000001) => 010_000_010_0000001 = 16'b0100_0001_0000_0001 = 16'h4101
        // Addr 2: ADD R3, R1, R2  => Op(001)|Rs(001)|Rt(010)|Rd(011)|0000 => 001_001_010_011_0000 = 16'b0010_0101_0011_0000 = 16'h2530
        // Addr 3: SW R3, R0, 2    => Op(011)|Rs(000)|Rt(011)|Imm(0000010) => 011_000_011_0000010 = 16'b0110_0001_1000_0010 = 16'h6182
        // Addr 4: BEQ R0, R0, 2   => Op(100)|Rs(000)|Rt(000)|Imm(0000010) => 100_000_000_0000010 = 16'b1000_0000_0000_0010 = 16'h8002
        // Addr 5: NOP             => Op(000)............................. => 16'h0000
        // Addr 6: NOP             => Op(000)............................. => 16'h0000
        // Addr 7: LW R4, R0, 2    => (Branch Target) Loads saved result back to R4
        //         Op(010)|Rs(000)|Rt(100)|Imm(0000010) => 010_000_100_0000010 = 16'b0100_0010_0000_0010 = 16'h4202

        memory[0] = 16'h4080; // LW R1, 0(R0)
        memory[1] = 16'h4101; // LW R2, 1(R0)
        memory[2] = 16'h2530; // ADD R3, R1, R2
        memory[3] = 16'h6182; // SW R3, 2(R0)
        memory[4] = 16'h8002; // BEQ R0, R0, 2 -> jumps to PC 4 + 1 + 2 = PC 7
        memory[5] = 16'h0000; // NOP (skipped)
        memory[6] = 16'h0000; // NOP (skipped)
        memory[7] = 16'h4202; // LW R4, 2(R0) -> R4 should get R1+R2
    end

    assign instr = memory[addr[7:0]];

endmodule

pc.v
module pc(input clk, input [15:0] next_pc, output reg [15:0] pc);
    initial begin
    pc = 0;
    end
    always @(posedge clk)
        pc <= next_pc;
endmodule

top.v
module top(input clk);

    wire [15:0] pc, instr, rd1, rd2, rd_val, alu_out, mem_out, next_pc;
    wire [3:0] opcode = instr[15:12];
    wire [3:0] rd = instr[11:8];
    wire [3:0] rs1 = instr[7:4];
    wire [3:0] rs2 = instr[3:0];

    wire regwrite, memwrite, alusrc, memtoreg, branch;
    wire [2:0] aluop;
    wire zero;

    pc PC(clk, next_pc, pc);
    imem IM(pc, instr);
    regfile RF(clk, regwrite, rs1, rs2, rd, memtoreg ? mem_out : alu_out, rd1, rd2, rd_val);
    alu ALU(rd1, alusrc ? {12'b0, rs2} : rd2, aluop, alu_out, zero);
    dmem DM(clk, memwrite, alu_out, rd_val, mem_out);
    control CU(opcode, regwrite, memwrite, alusrc, memtoreg, branch, aluop);

    assign next_pc = branch && zero ? pc + 2 : pc + 1;

endmodule

testbench.v
module testbench;

    reg clk = 0;
    top uut(clk);

    always #5 clk = ~clk;

    initial begin
        $dumpfile("wave.vcd");
        $dumpvars(0, testbench);

        #100;

        $display("--- Execution Results ---");
        $display("R1 = %d", uut.RF.regs[1]);
        $display("R2 = %d", uut.RF.regs[2]);
        $display("R3 = %d", uut.RF.regs[3]);
        $display("R4 = %d", uut.RF.regs[4]);
        $display("R5 = %d", uut.RF.regs[5]);
        $display("R6 = %d", uut.RF.regs[6]);
        $display("-------------------------");

        $finish;
    end

endmodule

wave.vcd
$date
	Tue Mar 10 08:51:04 2026
$end
$version
	Icarus Verilog
$end
$timescale
	1s
$end
$scope module testbench $end
$var reg 1 ! clk $end
$scope module uut $end
$var wire 1 ! clk $end
$var wire 1 " zero $end
$var wire 4 # rs2 [3:0] $end
$var wire 4 $ rs1 [3:0] $end
$var wire 1 % regwrite $end
$var wire 16 & rd_val [15:0] $end
$var wire 16 ' rd2 [15:0] $end
$var wire 16 ( rd1 [15:0] $end
$var wire 4 ) rd [3:0] $end
$var wire 16 * pc [15:0] $end
$var wire 4 + opcode [3:0] $end
$var wire 16 , next_pc [15:0] $end
$var wire 1 - memwrite $end
$var wire 1 . memtoreg $end
$var wire 16 / mem_out [15:0] $end
$var wire 16 0 instr [15:0] $end
$var wire 1 1 branch $end
$var wire 1 2 alusrc $end
$var wire 3 3 aluop [2:0] $end
$var wire 16 4 alu_out [15:0] $end
$scope module ALU $end
$var wire 16 5 b [15:0] $end
$var wire 1 " zero $end
$var wire 3 6 op [2:0] $end
$var wire 16 7 a [15:0] $end
$var reg 16 8 result [15:0] $end
$upscope $end
$scope module CU $end
$var wire 4 9 opcode [3:0] $end
$var reg 3 : aluop [2:0] $end
$var reg 1 2 alusrc $end
$var reg 1 1 branch $end
$var reg 1 . memtoreg $end
$var reg 1 - memwrite $end
$var reg 1 % regwrite $end
$upscope $end
$scope module DM $end
$var wire 16 ; addr [15:0] $end
$var wire 1 ! clk $end
$var wire 16 < rd [15:0] $end
$var wire 1 - we $end
$var wire 16 = wd [15:0] $end
$var integer 32 > i [31:0] $end
$upscope $end
$scope module IM $end
$var wire 16 ? instr [15:0] $end
$var wire 16 @ addr [15:0] $end
$upscope $end
$scope module PC $end
$var wire 1 ! clk $end
$var wire 16 A next_pc [15:0] $end
$var reg 16 B pc [15:0] $end
$upscope $end
$scope module RF $end
$var wire 1 ! clk $end
$var wire 4 C rd [3:0] $end
$var wire 16 D rd1 [15:0] $end
$var wire 16 E rd2 [15:0] $end
$var wire 16 F rd_val [15:0] $end
$var wire 4 G rs1 [3:0] $end
$var wire 4 H rs2 [3:0] $end
$var wire 16 I wd [15:0] $end
$var wire 1 % we $end
$var integer 32 J i [31:0] $end
$upscope $end
$upscope $end
$upscope $end
$enddefinitions $end
$comment Show the parameter values. $end
$dumpall
$end
#0
$dumpvars
b10000 J
b101 I
b101 H
b0 G
b0 F
b0 E
b0 D
b1 C
b0 B
b1 A
b0 @
b10000100000101 ?
b10000 >
b0 =
b0 <
b101 ;
b0 :
b10 9
b101 8
b0 7
b0 6
b101 5
b101 4
b0 3
12
01
b10000100000101 0
b0 /
0.
0-
b1 ,
b10 +
b0 *
b1 )
b0 (
b0 '
b0 &
1%
b0 $
b101 #
0"
0!
$end
#5
b11 I
b11 4
b11 8
b11 ;
b11 5
b11 #
b11 H
b10 )
b10 C
b10 ,
b10 A
b10001000000011 0
b10001000000011 ?
b1 *
b1 @
b1 B
b0 &
b0 F
1!
#10
0!
#15
b1000 I
b1000 4
b1000 8
b1000 ;
02
1%
b11 '
b11 =
b11 E
b10 #
b10 H
b101 (
b101 7
b101 D
b1 $
b1 G
b11 )
b11 C
b1 +
b1 9
b11 ,
b11 A
b0 &
b0 F
b1001100010010 0
b1001100010010 ?
b10 *
b10 @
b10 B
1!
#20
0!
#25
b101 I
b101 4
b101 8
b101 ;
b1 3
b1 6
b1 :
1%
b1000 (
b1000 7
b1000 D
b11 $
b11 G
b100 )
b100 C
b11 +
b11 9
b100 ,
b100 A
b11010000110010 0
b11010000110010 ?
b11 *
b11 @
b11 B
b0 &
b0 F
1!
#30
0!
#35
b0 I
1"
b0 4
b0 8
b0 ;
b101 5
b10 3
b10 6
b10 :
1%
b101 '
b101 =
b101 E
b1 #
b1 H
b101 )
b101 C
b100 +
b100 9
b101 ,
b101 A
b0 &
b0 F
b100010100110001 0
b100010100110001 ?
b100 *
b100 @
b100 B
1!
#40
0!
#45
b101 I
0"
b101 4
b101 8
b101 ;
b11 3
b11 6
b11 :
1%
b100 #
b100 H
b0 (
b0 7
b0 D
b101 $
b101 G
b110 )
b110 C
b101 +
b101 9
b110 ,
b110 A
b101011001010100 0
b101011001010100 ?
b101 *
b101 @
b101 B
1!
#50
0!
#55
b0 I
1"
b0 4
b0 8
b0 ;
b0 5
b0 3
b0 6
b0 :
0%
b0 '
b0 =
b0 E
b0 #
b0 H
b0 $
b0 G
b0 )
b0 C
b0 +
b0 9
b111 ,
b111 A
b0 &
b0 F
b0 0
b0 ?
b110 *
b110 @
b110 B
1!
#60
0!
#65
bx /
bx <
bx I
bx 5
x"
bx 4
bx 8
bx ;
bx '
bx =
bx E
bx #
bx H
bx (
bx 7
bx D
bx $
bx G
bx &
bx F
bx )
bx C
bx +
bx 9
b1000 ,
b1000 A
bx 0
bx ?
b111 *
b111 @
b111 B
1!
#70
0!
#75
b1001 ,
b1001 A
b1000 *
b1000 @
b1000 B
1!
#80
0!
#85
b1010 ,
b1010 A
b1001 *
b1001 @
b1001 B
1!
#90
0!
#95
b1011 ,
b1011 A
b1010 *
b1010 @
b1010 B
1!
