control.v
module control(input [3:0] opcode,
               output reg regwrite, memwrite,
               output reg alusrc, memtoreg,
               output reg branch,
               output reg [2:0] aluop);

    always @(*) begin
        regwrite = 0;
        memwrite = 0;
        alusrc   = 0;
        memtoreg = 0;
        branch   = 0;
        aluop    = 0;
        case(opcode)
            4'h1: begin // add
                regwrite=1; alusrc=0; memtoreg=0; memwrite=0; branch=0; aluop=3'b000;
            end
            4'h2: begin // addi
                regwrite=1; alusrc=1; memtoreg=0; memwrite=0; branch=0; aluop=3'b000;
            end
            4'h3: begin // sub
                regwrite=1; alusrc=0; memtoreg=0; memwrite=0; branch=0; aluop=3'b001;
            end
            4'h4: begin // and
                regwrite=1; alusrc=0; memtoreg=0; memwrite=0; branch=0; aluop=3'b010;
            end
            4'h5: begin // or
                regwrite=1; alusrc=0; memtoreg=0; memwrite=0; branch=0; aluop=3'b011;
            end
            default: begin // nop
                regwrite = 0;
                memwrite = 0;
                alusrc   = 0;
                memtoreg = 0;
                branch   = 0;
                aluop    = 0;
            end
        endcase
    end
endmodule

dmem.v
module dmem(input clk,
            input we,
            input [15:0] addr,
            input [15:0] wd,
            output [15:0] rd);

    reg [15:0] memory [0:15];

    assign rd = memory[addr[3:0]];

        integer i;

        initial begin
        for (i = 0; i < 16; i = i + 1)
                memory[i] = 0;
        end
    always @(posedge clk)
        if (we) memory[addr[3:0]] <= wd;
endmodule

alu.v
module alu(input [15:0] a, b,
           input [2:0] op,
           output reg [15:0] result,
           output zero);

    always @(*) begin
        case(op)
            3'b000: result = a + b;
            3'b001: result = a - b;
            3'b010: result = a & b;
            3'b011: result = a | b;
            default: result = 0;
        endcase
    end

    assign zero = (result == 0);
endmodule

regfile.v
module regfile(input clk,
               input we,
               input [3:0] rs1, rs2, rd,
               input [15:0] wd,
               output [15:0] rd1, rd2);

    reg [15:0] regs [0:15];

    assign rd1 = regs[rs1];
    assign rd2 = regs[rs2];

    integer i;
    initial begin
      for(i=0;i<16;i=i+1)
        regs[i]=0;
    end

    always @(posedge clk)
        if (we) regs[rd] <= wd;
endmodule

imem.v
module imem(input [15:0] addr, output [15:0] instr);

    reg [15:0] memory [0:15];

    initial begin
        memory[0] = 16'h2105;   // addi r1, r0, 5  (r1 = 5)
        memory[1] = 16'h2203;   // addi r2, r0, 3  (r2 = 3)
        memory[2] = 16'h1312;   // add r3, r1, r2  (r3 = 8)
        memory[3] = 16'h3432;   // sub r4, r3, r2  (r4 = 5)
        memory[4] = 16'h4531;   // and r5, r3, r1  (r5 = 8 & 5 = 1000 & 0101 = 0)
        memory[5] = 16'h5654;   // or r6, r5, r4   (r6 = 0 | 5 = 5)
        memory[6] = 16'h0000;   // nop
    end

    assign instr = memory[addr];
endmodule

pc.v
module pc(input clk, input [15:0] next_pc, output reg [15:0] pc);
    initial begin
    pc = 0;
    end
    always @(posedge clk)
        pc <= next_pc;
endmodule

top.v
module top(input clk);

    wire [15:0] pc, instr, rd1, rd2, alu_out, mem_out, next_pc;
    wire [3:0] opcode = instr[15:12];
    wire [3:0] rd = instr[11:8];
    wire [3:0] rs1 = instr[7:4];
    wire [3:0] rs2 = instr[3:0];

    wire regwrite, memwrite, alusrc, memtoreg, branch;
    wire [2:0] aluop;
    wire zero;

    pc PC(clk, next_pc, pc);
    imem IM(pc, instr);
    regfile RF(clk, regwrite, rs1, rs2, rd, memtoreg ? mem_out : alu_out, rd1, rd2);
    alu ALU(rd1, alusrc ? rs2 : rd2, aluop, alu_out, zero);
    dmem DM(clk, memwrite, alu_out, rd2, mem_out);
    control CU(opcode, regwrite, memwrite, alusrc, memtoreg, branch, aluop);

    assign next_pc = branch && zero ? pc + 2 : pc + 1;

endmodule

testbench.v
module testbench;

    reg clk = 0;
    top uut(clk);

    always #5 clk = ~clk;

    initial begin
        $dumpfile("wave.vcd");
        $dumpvars(0, testbench);

        #100;

        $display("--- Execution Results ---");
        $display("R1 = %d", uut.RF.regs[1]);
        $display("R2 = %d", uut.RF.regs[2]);
        $display("R3 = %d", uut.RF.regs[3]);
        $display("R4 = %d", uut.RF.regs[4]);
        $display("R5 = %d", uut.RF.regs[5]);
        $display("R6 = %d", uut.RF.regs[6]);
        $display("-------------------------");

        $finish;
    end

endmodule

wave.vcd
$date
	Mon Mar 09 22:07:15 2026
$end
$version
	Icarus Verilog
$end
$timescale
	1s
$end
$scope module testbench $end
$var reg 1 ! clk $end
$scope module uut $end
$var wire 1 ! clk $end
$var wire 1 " zero $end
$var wire 4 # rs2 [3:0] $end
$var wire 4 $ rs1 [3:0] $end
$var wire 1 % regwrite $end
$var wire 16 & rd2 [15:0] $end
$var wire 16 ' rd1 [15:0] $end
$var wire 4 ( rd [3:0] $end
$var wire 16 ) pc [15:0] $end
$var wire 4 * opcode [3:0] $end
$var wire 16 + next_pc [15:0] $end
$var wire 1 , memwrite $end
$var wire 1 - memtoreg $end
$var wire 16 . mem_out [15:0] $end
$var wire 16 / instr [15:0] $end
$var wire 1 0 branch $end
$var wire 1 1 alusrc $end
$var wire 3 2 aluop [2:0] $end
$var wire 16 3 alu_out [15:0] $end
$scope module ALU $end
$var wire 16 4 b [15:0] $end
$var wire 1 " zero $end
$var wire 3 5 op [2:0] $end
$var wire 16 6 a [15:0] $end
$var reg 16 7 result [15:0] $end
$upscope $end
$scope module CU $end
$var wire 4 8 opcode [3:0] $end
$var reg 3 9 aluop [2:0] $end
$var reg 1 1 alusrc $end
$var reg 1 0 branch $end
$var reg 1 - memtoreg $end
$var reg 1 , memwrite $end
$var reg 1 % regwrite $end
$upscope $end
$scope module DM $end
$var wire 16 : addr [15:0] $end
$var wire 1 ! clk $end
$var wire 16 ; rd [15:0] $end
$var wire 1 , we $end
$var wire 16 < wd [15:0] $end
$var integer 32 = i [31:0] $end
$upscope $end
$scope module IM $end
$var wire 16 > instr [15:0] $end
$var wire 16 ? addr [15:0] $end
$upscope $end
$scope module PC $end
$var wire 1 ! clk $end
$var wire 16 @ next_pc [15:0] $end
$var reg 16 A pc [15:0] $end
$upscope $end
$scope module RF $end
$var wire 1 ! clk $end
$var wire 4 B rd [3:0] $end
$var wire 16 C rd1 [15:0] $end
$var wire 16 D rd2 [15:0] $end
$var wire 4 E rs1 [3:0] $end
$var wire 4 F rs2 [3:0] $end
$var wire 16 G wd [15:0] $end
$var wire 1 % we $end
$var integer 32 H i [31:0] $end
$upscope $end
$upscope $end
$upscope $end
$enddefinitions $end
$comment Show the parameter values. $end
$dumpall
$end
#0
$dumpvars
b10000 H
b101 G
b101 F
b0 E
b0 D
b0 C
b1 B
b0 A
b1 @
b0 ?
b10000100000101 >
b10000 =
b0 <
b0 ;
b101 :
b0 9
b10 8
b101 7
b0 6
b0 5
b101 4
b101 3
b0 2
11
00
b10000100000101 /
b0 .
0-
0,
b1 +
b10 *
b0 )
b1 (
b0 '
b0 &
1%
b0 $
b101 #
0"
0!
$end
#5
b11 G
b11 3
b11 7
b11 :
b11 4
b11 #
b11 F
b10 (
b10 B
b10 +
b10 @
b10001000000011 /
b10001000000011 >
b1 )
b1 ?
b1 A
1!
#10
0!
#15
b1000 G
b1000 3
b1000 7
b1000 :
01
1%
b11 &
b11 <
b11 D
b10 #
b10 F
b101 '
b101 6
b101 C
b1 $
b1 E
b11 (
b11 B
b1 *
b1 8
b11 +
b11 @
b1001100010010 /
b1001100010010 >
b10 )
b10 ?
b10 A
1!
#20
0!
#25
b101 G
b101 3
b101 7
b101 :
b1 2
b1 5
b1 9
1%
b1000 '
b1000 6
b1000 C
b11 $
b11 E
b100 (
b100 B
b11 *
b11 8
b100 +
b100 @
b11010000110010 /
b11010000110010 >
b11 )
b11 ?
b11 A
1!
#30
0!
#35
b0 G
1"
b0 3
b0 7
b0 :
b101 4
b10 2
b10 5
b10 9
1%
b101 &
b101 <
b101 D
b1 #
b1 F
b101 (
b101 B
b100 *
b100 8
b101 +
b101 @
b100010100110001 /
b100010100110001 >
b100 )
b100 ?
b100 A
1!
#40
0!
#45
b101 G
0"
b101 3
b101 7
b101 :
b11 2
b11 5
b11 9
1%
b100 #
b100 F
b0 '
b0 6
b0 C
b101 $
b101 E
b110 (
b110 B
b101 *
b101 8
b110 +
b110 @
b101011001010100 /
b101011001010100 >
b101 )
b101 ?
b101 A
1!
#50
0!
#55
b0 G
1"
b0 3
b0 7
b0 :
b0 4
b0 2
b0 5
b0 9
0%
b0 &
b0 <
b0 D
b0 #
b0 F
b0 $
b0 E
b0 (
b0 B
b0 *
b0 8
b111 +
b111 @
b0 /
b0 >
b110 )
b110 ?
b110 A
1!
#60
0!
#65
bx G
bx 4
x"
bx .
bx ;
bx 3
bx 7
bx :
bx &
bx <
bx D
bx #
bx F
bx '
bx 6
bx C
bx $
bx E
bx (
bx B
bx *
bx 8
b1000 +
b1000 @
bx /
bx >
b111 )
b111 ?
b111 A
1!
#70
0!
#75
b1001 +
b1001 @
b1000 )
b1000 ?
b1000 A
1!
#80
0!
#85
b1010 +
b1010 @
b1001 )
b1001 ?
b1001 A
1!
#90
0!
#95
b1011 +
b1011 @
b1010 )
b1010 ?
b1010 A
1!
